[
  {
    "titre": "Première Guerre mondiale - Quiz CM2",
    "fichier": "quizz_1746882674.json"
  },
  {
    "titre": "Evaluation Physique Chimie 4ème - Date",
    "fichier": "quizz_1746974379.json"
  },
  {
    "titre": "Quiz de Probabilités - Niveau 4ème",
    "fichier": "quizz_1746974983.json"
  },
  {
    "titre": "Quiz Physique Chimie N°2 - Transformations chimiques, combustion et solubilité",
    "fichier": "quizz_1746977270.json"
  },
  {
    "titre": "Quiz sur la Première Guerre mondiale - CM2",
    "fichier": "quizz_1746985055.json"
  },
  {
    "titre": "Quiz Maths - Sophia",
    "fichier": "quizz_1747576474.json"
  },
  {
    "titre": "Quiz Mathématiques - Probabilités et Fractions - Niveau 4ème",
    "fichier": "quizz_1747576519.json"
  }
]
